alibabacloud_sae20190506/__init__.py
alibabacloud_sae20190506/client.py
alibabacloud_sae20190506/models/__init__.py
alibabacloud_sae20190506/models/_abort_and_rollback_change_order_request.py
alibabacloud_sae20190506/models/_abort_and_rollback_change_order_response.py
alibabacloud_sae20190506/models/_abort_and_rollback_change_order_response_body.py
alibabacloud_sae20190506/models/_abort_change_order_request.py
alibabacloud_sae20190506/models/_abort_change_order_response.py
alibabacloud_sae20190506/models/_abort_change_order_response_body.py
alibabacloud_sae20190506/models/_acl_config.py
alibabacloud_sae20190506/models/_acl_entry_config.py
alibabacloud_sae20190506/models/_app_stack_instance.py
alibabacloud_sae20190506/models/_app_stack_resource.py
alibabacloud_sae20190506/models/_app_stack_task.py
alibabacloud_sae20190506/models/_application.py
alibabacloud_sae20190506/models/_application_status.py
alibabacloud_sae20190506/models/_application_with_status.py
alibabacloud_sae20190506/models/_arms_config.py
alibabacloud_sae20190506/models/_batch_restart_applications_request.py
alibabacloud_sae20190506/models/_batch_restart_applications_response.py
alibabacloud_sae20190506/models/_batch_restart_applications_response_body.py
alibabacloud_sae20190506/models/_batch_start_applications_request.py
alibabacloud_sae20190506/models/_batch_start_applications_response.py
alibabacloud_sae20190506/models/_batch_start_applications_response_body.py
alibabacloud_sae20190506/models/_batch_stop_applications_request.py
alibabacloud_sae20190506/models/_batch_stop_applications_response.py
alibabacloud_sae20190506/models/_batch_stop_applications_response_body.py
alibabacloud_sae20190506/models/_bind_nlb_request.py
alibabacloud_sae20190506/models/_bind_nlb_response.py
alibabacloud_sae20190506/models/_bind_nlb_response_body.py
alibabacloud_sae20190506/models/_bind_slb_request.py
alibabacloud_sae20190506/models/_bind_slb_response.py
alibabacloud_sae20190506/models/_bind_slb_response_body.py
alibabacloud_sae20190506-2.11.0.dist-info/LICENSE
alibabacloud_sae20190506-2.11.0.dist-info/METADATA
alibabacloud_sae20190506-2.11.0.dist-info/WHEEL
alibabacloud_sae20190506-2.11.0.dist-info/top_level.txt
alibabacloud_sae20190506-2.11.0.dist-info/RECORD
